fasterbench/__init__.py
fasterbench/_modidx.py
fasterbench/benchmark.py
fasterbench-0.0.6.dist-info/LICENSE
fasterbench-0.0.6.dist-info/METADATA
fasterbench-0.0.6.dist-info/WHEEL
fasterbench-0.0.6.dist-info/entry_points.txt
fasterbench-0.0.6.dist-info/top_level.txt
fasterbench-0.0.6.dist-info/RECORD
