Metadata-Version: 2.1
Name: fasterbench
Version: 0.0.6
Summary: A library for benchmarking AI models
Home-page: https://github.com/FasterAI-Labs/fasterbench
Author: nathanhubens
Author-email: nathan.hubens@gmail.com
License: Apache Software License 2.0
Keywords: nbdev jupyter notebook python
Classifier: Development Status :: 4 - Beta
Classifier: Intended Audience :: Developers
Classifier: Natural Language :: English
Classifier: Programming Language :: Python :: 3.7
Classifier: Programming Language :: Python :: 3.8
Classifier: Programming Language :: Python :: 3.9
Classifier: Programming Language :: Python :: 3.10
Classifier: License :: OSI Approved :: Apache Software License
Requires-Python: >=3.7
License-File: LICENSE
Requires-Dist: torch
Requires-Dist: fastcore
Requires-Dist: prettytable
Requires-Dist: tqdm
Requires-Dist: codecarbon
Requires-Dist: torchprofile
Requires-Dist: thop
Provides-Extra: dev
